openinference/instrumentation/langchain/__init__.py
openinference/instrumentation/langchain/_tracer.py
openinference/instrumentation/langchain/package.py
openinference/instrumentation/langchain/py.typed
openinference/instrumentation/langchain/version.py
openinference_instrumentation_langchain-0.1.58.dist-info/METADATA
openinference_instrumentation_langchain-0.1.58.dist-info/WHEEL
openinference_instrumentation_langchain-0.1.58.dist-info/entry_points.txt
openinference_instrumentation_langchain-0.1.58.dist-info/licenses/LICENSE
openinference_instrumentation_langchain-0.1.58.dist-info/RECORD
